surelink/__init__.py
surelink/helpers.py
surelink/tests.py
surelink-1.1.1.dist-info/METADATA
surelink-1.1.1.dist-info/WHEEL
surelink-1.1.1.dist-info/top_level.txt
surelink-1.1.1.dist-info/RECORD
