Metadata-Version: 2.1
Name: surelink
Version: 1.1.1
Summary: generate secure video links
Home-page: https://github.com/ccnmtl/surelink/
Author: Anders Pearson
Author-email: anders@columbia.edu
License: BSD
Platform: any
